smftools/__init__.py
smftools/_settings.py
smftools/_version.py
smftools/cli.py
smftools/load_adata.py
smftools/readwrite.py
smftools/config/__init__.py
smftools/config/conversion.yaml
smftools/config/deaminase.yaml
smftools/config/default.yaml
smftools/config/direct.yaml
smftools/config/experiment_config.py
smftools/datasets/F1_hybrid_NKG2A_enhander_promoter_GpC_conversion_SMF.h5ad.gz
smftools/datasets/F1_sample_sheet.csv
smftools/datasets/__init__.py
smftools/datasets/dCas9_m6A_invitro_kinetics.h5ad.gz
smftools/datasets/datasets.py
smftools/hmm/HMM.py
smftools/hmm/__init__.py
smftools/hmm/apply_hmm_batched.py
smftools/hmm/calculate_distances.py
smftools/hmm/call_hmm_peaks.py
smftools/hmm/display_hmm.py
smftools/hmm/hmm_readwrite.py
smftools/hmm/nucleosome_hmm_refinement.py
smftools/hmm/train_hmm.py
smftools/informatics/__init__.py
smftools/informatics/basecall_pod5s.py
smftools/informatics/fast5_to_pod5.py
smftools/informatics/readwrite.py
smftools/informatics/subsample_fasta_from_bed.py
smftools/informatics/subsample_pod5.py
smftools/informatics/archived/bam_conversion.py
smftools/informatics/archived/bam_direct.py
smftools/informatics/archived/basecalls_to_adata.py
smftools/informatics/archived/conversion_smf.py
smftools/informatics/archived/deaminase_smf.py
smftools/informatics/archived/direct_smf.py
smftools/informatics/archived/print_bam_query_seq.py
smftools/informatics/helpers/__init__.py
smftools/informatics/helpers/align_and_sort_BAM.py
smftools/informatics/helpers/aligned_BAM_to_bed.py
smftools/informatics/helpers/bam_qc.py
smftools/informatics/helpers/bed_to_bigwig.py
smftools/informatics/helpers/binarize_converted_base_identities.py
smftools/informatics/helpers/canoncall.py
smftools/informatics/helpers/complement_base_list.py
smftools/informatics/helpers/concatenate_fastqs_to_bam.py
smftools/informatics/helpers/converted_BAM_to_adata.py
smftools/informatics/helpers/converted_BAM_to_adata_II.py
smftools/informatics/helpers/count_aligned_reads.py
smftools-0.2.1.dist-info/METADATA
smftools-0.2.1.dist-info/WHEEL
smftools-0.2.1.dist-info/entry_points.txt
smftools-0.2.1.dist-info/licenses/LICENSE
smftools-0.2.1.dist-info/RECORD
