Metadata-Version: 2.3
Name: smftools
Version: 0.2.1
Summary: Single Molecule Footprinting Analysis in Python.
Project-URL: Source, https://github.com/jkmckenna/smftools
Project-URL: Documentation, https://smftools.readthedocs.io/
Author: Joseph McKenna
Maintainer-email: Joseph McKenna <jkmckenna@berkeley.edu>
License: MIT License
License-File: LICENSE
Keywords: anndata,chromatin-accessibility,machine-learning,nanopore,protein-dna-binding,single-locus,single-molecule-footprinting
Classifier: Development Status :: 2 - Pre-Alpha
Classifier: Environment :: Console
Classifier: Intended Audience :: Developers
Classifier: Intended Audience :: Science/Research
Classifier: License :: OSI Approved :: MIT License
Classifier: Natural Language :: English
Classifier: Operating System :: MacOS :: MacOS X
Classifier: Programming Language :: Python :: 3
Classifier: Programming Language :: Python :: 3.9
Classifier: Programming Language :: Python :: 3.10
Classifier: Programming Language :: Python :: 3.11
Classifier: Programming Language :: Python :: 3.12
Classifier: Topic :: Scientific/Engineering :: Bio-Informatics
Classifier: Topic :: Scientific/Engineering :: Visualization
Requires-Python: >=3.9
Requires-Dist: anndata>=0.10.0
Requires-Dist: biopython>=1.79
Requires-Dist: captum
Requires-Dist: click
Requires-Dist: fastcluster
Requires-Dist: hydra-core
Requires-Dist: igraph
Requires-Dist: leidenalg
Requires-Dist: lightning
Requires-Dist: multiqc
Requires-Dist: networkx>=3.2
Requires-Dist: numpy<2,>=1.22.0
Requires-Dist: omegaconf
Requires-Dist: pandas>=1.4.2
Requires-Dist: pod5>=0.1.21
Requires-Dist: pomegranate>=1.0.0
Requires-Dist: pyfaidx>=0.8.0
Requires-Dist: pysam>=0.19.1
Requires-Dist: scanpy>=1.9
Requires-Dist: scikit-learn>=1.0.2
Requires-Dist: scipy>=1.7.3
Requires-Dist: seaborn>=0.11
Requires-Dist: shap
Requires-Dist: torch>=1.9.0
Requires-Dist: tqdm
Requires-Dist: upsetplot
Requires-Dist: wandb
Provides-Extra: docs
Requires-Dist: ipython>=7.20; extra == 'docs'
Requires-Dist: matplotlib!=3.6.1; extra == 'docs'
Requires-Dist: myst-nb>=1; extra == 'docs'
Requires-Dist: myst-parser>=2; extra == 'docs'
Requires-Dist: nbsphinx>=0.9; extra == 'docs'
Requires-Dist: readthedocs-sphinx-search; extra == 'docs'
Requires-Dist: setuptools; extra == 'docs'
Requires-Dist: sphinx-autodoc-typehints>=1.25.2; extra == 'docs'
Requires-Dist: sphinx-book-theme>=1.1.0; extra == 'docs'
Requires-Dist: sphinx-copybutton; extra == 'docs'
Requires-Dist: sphinx-design; extra == 'docs'
Requires-Dist: sphinx>=7; extra == 'docs'
Requires-Dist: sphinxcontrib-bibtex; extra == 'docs'
Requires-Dist: sphinxext-opengraph; extra == 'docs'
Provides-Extra: tests
Requires-Dist: pytest; extra == 'tests'
Requires-Dist: pytest-cov; extra == 'tests'
